django_burl/__init__.py
django_burl/admin.py
django_burl/apps.py
django_burl/conf.py
django_burl/database.py
django_burl/models.py
django_burl/urls.py
django_burl/utils.py
django_burl/views.py
django_burl/api/__init__.py
django_burl/api/v1/__init__.py
django_burl/api/v1/serializers.py
django_burl/api/v1/urls.py
django_burl/api/v1/views.py
django_burl/api/v1/viewsets.py
django_burl/api/v2/__init__.py
django_burl/api/v2/serializers.py
django_burl/api/v2/urls.py
django_burl/api/v2/views.py
django_burl/api/v2/viewsets.py
django_burl/management/__init__.py
django_burl/management/commands/__init__.py
django_burl/management/commands/burl_domain_user.py
django_burl/management/commands/burl_plos_import.py
django_burl/management/commands/burl_set_default_site.py
django_burl/management/commands/burl_v1_import.py
django_burl/migrations/0001_initial.py
django_burl/migrations/0002_auto_20220217_1532.py
django_burl/migrations/0003_briefurl_site_alter_briefurl_burl_and_more.py
django_burl/migrations/0004_remove_briefurl_burl_site_enabled_and_more.py
django_burl/migrations/0005_briefurldomainuser.py
django_burl/migrations/0006_alter_briefurldomainuser_unique_together.py
django_burl/migrations/0007_briefurldefaultredirect.py
django_burl/migrations/0008_alter_briefurldefaultredirect_site.py
django_burl/migrations/0009_alter_briefurldefaultredirect_site.py
django_burl/migrations/__init__.py
django_burl/tests/__init__.py
django_burl/tests/settings.py
django_burl/tests/test_api.py
django_burl/tests/test_forms.py
django_burl/tests/test_models.py
django_burl/tests/test_utils.py
django_burl/tests/test_views.py
django_burl-1.0.4.dist-info/AUTHORS
django_burl-1.0.4.dist-info/LICENSE
django_burl-1.0.4.dist-info/METADATA
django_burl-1.0.4.dist-info/WHEEL
django_burl-1.0.4.dist-info/pbr.json
django_burl-1.0.4.dist-info/top_level.txt
django_burl-1.0.4.dist-info/RECORD
