Metadata-Version: 2.1
Name: django-burl
Version: 1.0.4
Summary: A Django app for shortening URLs
Home-page: https://gitlab.com/wryfi/django-burl
Author: Christian Haumesser
Author-email: ch@wryfi.net
License: MIT
Platform: UNKNOWN
Classifier: Environment :: Web Environment
Classifier: Framework :: Django
Classifier: Framework :: Django :: 2
Classifier: Framework :: Django :: 3
Classifier: Framework :: Django :: 4
Classifier: Intended Audience :: Developers
Classifier: License :: OSI Approved :: MIT License
Classifier: Operating System :: OS Independent
Classifier: Programming Language :: Python
Classifier: Programming Language :: Python :: 3
Classifier: Programming Language :: Python :: 3 :: Only
Classifier: Programming Language :: Python :: 3.8
Classifier: Programming Language :: Python :: 3.9
Classifier: Programming Language :: Python :: 3.10
Classifier: Topic :: Internet :: WWW/HTTP
Classifier: Topic :: Internet :: WWW/HTTP :: Dynamic Content
Requires-Python: >=3.8
License-File: LICENSE
License-File: AUTHORS
Requires-Dist: Django (>=2.0)
Requires-Dist: django-filter
Requires-Dist: djangorestframework (<4.0)
Requires-Dist: djangorestframework-simplejwt (<=5.0)
Requires-Dist: hashids (<2.0)
Requires-Dist: requests
